beizer_curves.py
beizer_curves-0.0.1.dist-info/METADATA
beizer_curves-0.0.1.dist-info/WHEEL
beizer_curves-0.0.1.dist-info/top_level.txt
beizer_curves-0.0.1.dist-info/RECORD
