Metadata-Version: 2.1
Name: beizer-curves
Version: 0.0.1
Summary: A python library for generating beizer curves.
Home-page: https://github.com/Layerex/beizer-curves
Author: Layerex
Author-email: layerex@dismail.de
License: UNKNOWN
Platform: UNKNOWN
Classifier: Programming Language :: Python :: 3
Classifier: License :: OSI Approved :: Mozilla Public License 2.0 (MPL 2.0)
Classifier: Operating System :: OS Independent
Classifier: Topic :: Scientific/Engineering :: Mathematics
Classifier: Topic :: Software Development :: Libraries :: Python Modules
Requires-Dist: numpy
